initme
