Metadata-Version: 2.1
Name: initme
Version: 0.3.0
Summary: Create the __init__.py file in every single subdirectroy with a python folder
Home-page: https://github.com/George3d6/initme
Author: George Hosu
Author-email: george@cerebralab.com
License: MIT
Download-URL: https://pypi.org/project/initme/
Platform: UNKNOWN
Classifier: Programming Language :: Python :: 3
Classifier: Operating System :: OS Independent
Requires-Python: >=3.5
